seeq_ITV_visual/__init__.py
seeq_ITV_visual/_version.py
seeq_ITV_visual/pairplot.py
seeq_ITV_visual/pairplot_interactive.py
seeq_ITV_visual/violinplot.py
seeq_ITV_visual-0.1.4.dist-info/LICENSE
seeq_ITV_visual-0.1.4.dist-info/METADATA
seeq_ITV_visual-0.1.4.dist-info/WHEEL
seeq_ITV_visual-0.1.4.dist-info/top_level.txt
seeq_ITV_visual-0.1.4.dist-info/RECORD
