Metadata-Version: 2.1
Name: seeq-ITV-visual
Version: 0.1.4
Summary: Plotting add-ons for Seeq platform
Author-email: IT Vizion <support@itvizion.com>
Project-URL: Homepage, https://itvizion.github.io/seeq-itvizion-visualization-docs/
Classifier: Programming Language :: Python :: 3
Classifier: License :: Other/Proprietary License
Classifier: Operating System :: OS Independent
Requires-Python: >=3.7
License-File: LICENSE
